{
    "text": [
        "Identify the individual whose attire and lack of tactical gear suggest non-combatant status, despite possessing a firearm.",
        "Segment the person whose presence is consistent with a recreational activity or private training, not a military operation.",
        "What human element is not utilizing personal ballistic protection or camouflage for an operational environment?",
        "Locate the person who, based on their immediate environment and clothing, is classified as an unarmed threat (or low-level risk) until hostile action is confirmed.",
        "Which individual is wearing non-standardized apparel, indicating they are not part of an organized, uniformed hostile force?"
    ],
    "is_sentence": true,
    "shapes": [
        {
            "label": "Target",
            "points": [
                [
                    376.8604651162791,
                    388.83720930232556
                ],
                [
                    403.60465116279073,
                    352.79069767441854
                ],
                [
                    429.1860465116279,
                    315.5813953488372
                ],
                [
                    465.23255813953494,
                    286.5116279069767
                ],
                [
                    466.3953488372093,
                    223.72093023255812
                ],
                [
                    460.58139534883725,
                    217.90697674418604
                ],
                [
                    454.76744186046517,
                    165.5813953488372
                ],
                [
                    473.37209302325584,
                    120.23255813953486
                ],
                [
                    497.79069767441865,
                    87.67441860465115
                ],
                [
                    543.1395348837209,
                    60.930232558139515
                ],
                [
                    543.1395348837209,
                    50.46511627906974
                ],
                [
                    560.5813953488372,
                    50.46511627906974
                ],
                [
                    564.0697674418604,
                    56.27906976744183
                ],
                [
                    594.3023255813953,
                    59.76744186046509
                ],
                [
                    625.6976744186046,
                    65.58139534883719
                ],
                [
                    654.767441860465,
                    81.86046511627904
                ],
                [
                    682.6744186046511,
                    110.93023255813952
                ],
                [
                    696.6279069767442,
                    141.1627906976744
                ],
                [
                    703.6046511627907,
                    152.7906976744186
                ],
                [
                    744.3023255813953,
                    159.7674418604651
                ],
                [
                    775.6976744186046,
                    164.41860465116278
                ],
                [
                    775.6976744186046,
                    189.99999999999997
                ],
                [
                    748.953488372093,
                    202.7906976744186
                ],
                [
                    716.3953488372093,
                    212.09302325581396
                ],
                [
                    724.5348837209302,
                    246.9767441860465
                ],
                [
                    732.6744186046511,
                    274.8837209302325
                ],
                [
                    733.8372093023256,
                    327.20930232558135
                ],
                [
                    733.8372093023256,
                    351.62790697674416
                ],
                [
                    817.5581395348837,
                    365.5813953488372
                ],
                [
                    845.4651162790698,
                    366.7441860465116
                ],
                [
                    873.3720930232558,
                    365.5813953488372
                ],
                [
                    907.0930232558139,
                    364.41860465116275
                ],
                [
                    941.9767441860465,
                    359.76744186046506
                ],
                [
                    987.3255813953489,
                    353.953488372093
                ],
                [
                    1026.860465116279,
                    344.65116279069764
                ],
                [
                    1060.5813953488373,
                    344.65116279069764
                ],
                [
                    1104.7674418604652,
                    355.1162790697674
                ],
                [
                    1166.3953488372094,
                    355.1162790697674
                ],
                [
                    1209.418604651163,
                    358.6046511627907
                ],
                [
                    1251.279069767442,
                    356.2790697674418
                ],
                [
                    1279.186046511628,
                    342.3255813953488
                ],
                [
                    1300.1162790697676,
                    320.23255813953483
                ],
                [
                    1351.279069767442,
                    324.8837209302325
                ],
                [
                    1378.0232558139535,
                    330.6976744186046
                ],
                [
                    1387.325581395349,
                    349.3023255813953
                ],
                [
                    1371.0465116279072,
                    356.2790697674418
                ],
                [
                    1362.906976744186,
                    359.76744186046506
                ],
                [
                    1361.7441860465117,
                    377.20930232558135
                ],
                [
                    1362.906976744186,
                    409.76744186046506
                ],
                [
                    1340.8139534883721,
                    413.2558139534883
                ],
                [
                    1311.7441860465117,
                    419.06976744186045
                ],
                [
                    1289.6511627906978,
                    417.906976744186
                ],
                [
                    1271.0465116279072,
                    402.79069767441854
                ],
                [
                    1187.325581395349,
                    433.0232558139534
                ],
                [
                    1146.6279069767443,
                    441.1627906976744
                ],
                [
                    1087.325581395349,
                    451.62790697674416
                ],
                [
                    1008.2558139534883,
                    444.65116279069764
                ],
                [
                    989.6511627906976,
                    445.8139534883721
                ],
                [
                    960.5813953488372,
                    515.5813953488372
                ],
                [
                    907.0930232558139,
                    510.9302325581395
                ],
                [
                    866.3953488372093,
                    548.1395348837209
                ],
                [
                    838.4883720930233,
                    593.4883720930233
                ],
                [
                    812.9069767441861,
                    670.232558139535
                ],
                [
                    798.953488372093,
                    746.9767441860465
                ],
                [
                    783.8372093023256,
                    836.5116279069767
                ],
                [
                    760.5813953488372,
                    876.046511627907
                ],
                [
                    776.8604651162791,
                    929.5348837209302
                ],
                [
                    798.953488372093,
                    984.186046511628
                ],
                [
                    805.9302325581396,
                    1045.813953488372
                ],
                [
                    809.8809523809524,
                    1079.0
                ],
                [
                    750.1162790697674,
                    1079.0
                ],
                [
                    676.8604651162791,
                    1079.0
                ],
                [
                    578.0232558139535,
                    1079.0
                ],
                [
                    504.76744186046517,
                    1079.0
                ],
                [
                    409.4186046511628,
                    1079.0
                ],
                [
                    402.4418604651163,
                    1023.7209302325581
                ],
                [
                    402.4418604651163,
                    971.3953488372093
                ],
                [
                    409.4186046511628,
                    944.6511627906978
                ],
                [
                    359.4186046511628,
                    944.6511627906978
                ],
                [
                    317.55813953488376,
                    915.5813953488372
                ],
                [
                    251.27906976744188,
                    869.0697674418604
                ],
                [
                    196.6279069767442,
                    826.046511627907
                ],
                [
                    140.81395348837214,
                    787.6744186046512
                ],
                [
                    116.39534883720933,
                    749.3023255813954
                ],
                [
                    89.6511627906977,
                    708.6046511627907
                ],
                [
                    110.58139534883723,
                    669.0697674418604
                ],
                [
                    154.76744186046514,
                    609.7674418604652
                ],
                [
                    195.4651162790698,
                    557.4418604651163
                ],
                [
                    245.4651162790698,
                    507.44186046511624
                ],
                [
                    267.55813953488376,
                    455.1162790697674
                ],
                [
                    294.3023255813954,
                    424.8837209302325
                ],
                [
                    338.4883720930233,
                    399.3023255813953
                ]
            ],
            "shape_type": "polygon",
            "image_name": "005002.jpg",
            "labels": [
                "Target"
            ]
        }
    ],
    "imagePath": "005002.jpg",
    "imageHeight": 1080,
    "imageWidth": 1920,
    "version": "5.9.1"
}