{
    "text": [
        "Identify the rotary-wing platform designed for anti-armor and attack missions.",
        "Pinpoint the asset providing close air support from a helicopter.",
        "Which platform shown uses a coaxial rotor system for high-maneuverability attack runs?",
        "Tag the aerial asset that functions as a 'flying tank'.",
        "Locate the dedicated hunter-killer helicopter currently in flight."
    ],
    "is_sentence": true,
    "shapes": [
        {
            "label": "target",
            "points": [
                [
                    1100.780487804878,
                    559.4634146341463
                ],
                [
                    852.0,
                    539.951219512195
                ],
                [
                    842.2439024390244,
                    569.2195121951219
                ],
                [
                    1108.0975609756097,
                    598.4878048780487
                ],
                [
                    1076.3902439024391,
                    686.2926829268292
                ],
                [
                    1025.1707317073171,
                    725.3170731707316
                ],
                [
                    991.0243902439024,
                    708.2439024390243
                ],
                [
                    937.3658536585365,
                    793.6097560975609
                ],
                [
                    869.0731707317073,
                    810.6829268292682
                ],
                [
                    793.4634146341464,
                    757.0243902439023
                ],
                [
                    766.6341463414635,
                    786.2926829268291
                ],
                [
                    852.0,
                    893.6097560975609
                ],
                [
                    886.1463414634147,
                    886.2926829268291
                ],
                [
                    961.7560975609756,
                    847.2682926829267
                ],
                [
                    993.4634146341464,
                    876.5365853658535
                ],
                [
                    1020.2926829268292,
                    854.5853658536585
                ],
                [
                    1008.0975609756097,
                    835.0731707317073
                ],
                [
                    1149.560975609756,
                    783.8536585365853
                ],
                [
                    1139.8048780487804,
                    842.3902439024389
                ],
                [
                    1191.0243902439024,
                    825.3170731707316
                ],
                [
                    1215.4146341463415,
                    832.6341463414633
                ],
                [
                    1232.4878048780488,
                    810.6829268292682
                ],
                [
                    1225.1707317073171,
                    793.6097560975609
                ],
                [
                    1249.560975609756,
                    757.0243902439023
                ],
                [
                    1395.90243902439,
                    676.5365853658535
                ],
                [
                    1403.219512195122,
                    700.9268292682926
                ],
                [
                    1427.6097560975609,
                    698.4878048780487
                ],
                [
                    1469.0731707317073,
                    581.4146341463414
                ],
                [
                    1300.780487804878,
                    588.7317073170731
                ],
                [
                    1456.8780487804877,
                    527.7560975609755
                ],
                [
                    1456.8780487804877,
                    513.1219512195121
                ],
                [
                    1293.4634146341464,
                    566.780487804878
                ],
                [
                    1239.8048780487804,
                    542.3902439024389
                ],
                [
                    1195.9024390243903,
                    554.5853658536585
                ],
                [
                    1205.658536585366,
                    605.8048780487804
                ],
                [
                    1178.8292682926829,
                    605.8048780487804
                ],
                [
                    1166.6341463414633,
                    552.1463414634145
                ],
                [
                    1420.2926829268292,
                    308.2439024390244
                ],
                [
                    1400.780487804878,
                    303.3658536585366
                ],
                [
                    1154.439024390244,
                    525.3170731707316
                ],
                [
                    1130.0487804878048,
                    418.0
                ],
                [
                    1098.341463414634,
                    418.0
                ]
            ],
            "shape_type": "polygon",
            "image_name": "018732.jpg",
            "labels": [
                "target"
            ]
        }
    ],
    "imagePath": "018732.jpg",
    "imageHeight": 1536,
    "imageWidth": 2304,
    "version": "5.9.1"
}